mkstd/__init__.py
mkstd/standards/__init__.py
mkstd/standards/hdf5.py
mkstd/standards/json.py
mkstd/standards/standard.py
mkstd/standards/xml.py
mkstd/standards/yaml.py
mkstd/standards/hdfdict/__init__.py
mkstd/standards/hdfdict/hdfdict.py
mkstd/types/__init__.py
mkstd/types/array.py
mkstd/types/path.py
mkstd-0.0.10.dist-info/licenses/LICENSE
mkstd-0.0.10.dist-info/METADATA
mkstd-0.0.10.dist-info/WHEEL
mkstd-0.0.10.dist-info/top_level.txt
mkstd-0.0.10.dist-info/RECORD
