Metadata-Version: 2.4
Name: mkstd
Version: 0.0.10
Summary: Make standards compatible with HDF5/JSON/XML/YAML.
Author-email: Dilan Pathirana <dilan.pathirana@uni-bonn.de>
License: BSD 3-Clause License
Project-URL: Homepage, https://github.com/dilpath/mkstd
Keywords: standard,hdf5,json,xml,yaml
Classifier: License :: OSI Approved :: BSD License
Classifier: Programming Language :: Python
Classifier: Programming Language :: Python :: 3
Requires-Python: >=3.8
License-File: LICENSE
Requires-Dist: pydantic>=2.7.4
Requires-Dist: pydantic_numpy
Requires-Dist: h5py>=3.11
Requires-Dist: pyyaml>=6.0.2
Requires-Dist: oyaml>=1.0
Requires-Dist: defusedxml>=0.7.1
Requires-Dist: xmlschema>=3.3.1
Provides-Extra: dev
Requires-Dist: black; extra == "dev"
Requires-Dist: isort; extra == "dev"
Requires-Dist: pytest; extra == "dev"
Requires-Dist: pre-commit>=3.8.0; extra == "dev"
Provides-Extra: numpyv1
Requires-Dist: pydantic_numpy<6; extra == "numpyv1"
Requires-Dist: numpy<2; extra == "numpyv1"
Dynamic: license-file
